toolkit.py
astraSDK/__init__.py
astraSDK/apiresources.py
astraSDK/apps.py
astraSDK/asups.py
astraSDK/backups.py
astraSDK/buckets.py
astraSDK/clouds.py
astraSDK/clusters.py
astraSDK/common.py
astraSDK/credentials.py
astraSDK/entitlements.py
astraSDK/groups.py
astraSDK/hooks.py
astraSDK/k8s.py
astraSDK/namespaces.py
astraSDK/notifications.py
astraSDK/protections.py
astraSDK/replications.py
astraSDK/rolebindings.py
astraSDK/scripts.py
astraSDK/settings.py
astraSDK/snapshots.py
astraSDK/storagebackends.py
astraSDK/storageclasses.py
astraSDK/users.py
tkSrc/__init__.py
tkSrc/choices.py
tkSrc/classes.py
tkSrc/clone.py
tkSrc/copy.py
tkSrc/create.py
tkSrc/deploy.py
tkSrc/destroy.py
tkSrc/helpers.py
tkSrc/ipr.py
tkSrc/list.py
tkSrc/manage.py
tkSrc/parser.py
tkSrc/unmanage.py
tkSrc/update.py
tkSrc/templates/jinja/app.jinja
tkSrc/templates/jinja/appVault.jinja
tkSrc/templates/jinja/backup.jinja
tkSrc/templates/jinja/hook.jinja
tkSrc/templates/jinja/ipr.jinja
tkSrc/templates/jinja/protection.jinja
tkSrc/templates/jinja/restore.jinja
tkSrc/templates/jinja/snapshot.jinja
actoolkit-3.0.2.dist-info/LICENSE
actoolkit-3.0.2.dist-info/METADATA
actoolkit-3.0.2.dist-info/WHEEL
actoolkit-3.0.2.dist-info/entry_points.txt
actoolkit-3.0.2.dist-info/top_level.txt
actoolkit-3.0.2.dist-info/RECORD
