Metadata-Version: 2.1
Name: actoolkit
Version: 3.0.2
Summary: Toolkit and SDK for interacting with Astra Control
Home-page: https://github.com/NetApp/netapp-astra-toolkits
Author: Michael Haigh
Author-email: Michael.Haigh@netapp.com
Classifier: Programming Language :: Python :: 3
Classifier: License :: OSI Approved :: Apache Software License
Classifier: Operating System :: OS Independent
Requires-Python: >=3.8
License-File: LICENSE
Requires-Dist: Jinja2 >=3.1.2
Requires-Dist: kubernetes <=29.0.0,>=25.3.0
Requires-Dist: PyYAML <=6.0.1,>=6.0.0
Requires-Dist: requests ==2.32.2
Requires-Dist: tabulate <=0.9.0,>=0.8.9
Requires-Dist: urllib3 <=2.2.1,>=1.26.8
